mcp_glama_registry/__init__.py
mcp_glama_registry-0.1.1.dist-info/licenses/LICENSE
mcp_glama_registry-0.1.1.dist-info/METADATA
mcp_glama_registry-0.1.1.dist-info/WHEEL
mcp_glama_registry-0.1.1.dist-info/entry_points.txt
mcp_glama_registry-0.1.1.dist-info/top_level.txt
mcp_glama_registry-0.1.1.dist-info/RECORD
