Metadata-Version: 2.4
Name: mcp-glama-registry
Version: 0.1.1
Summary: MCP Registry Server for Glama MCP. Exposes a tool to search the Glama MCP registry for MCP servers.
Author-email: Yuri Golikov <iurii.golikov@gmail.com>
License-Expression: MIT
Project-URL: Homepage, https://github.com/meetmatt/glama-mcp-registry-mcp-server
Requires-Python: >=3.10
License-File: LICENSE
Requires-Dist: mcp[cli]>=1.9.1
Requires-Dist: ruff>=0.11.11
Dynamic: license-file
